[
  {
    "id": "chunk_001",
    "text": "原神是一款开放世界冒险游戏，玩家以旅行者身份在提瓦特大陆探索不同地区。",
    "source": "genshin_notes.txt"
  },
  {
    "id": "chunk_002",
    "text": "祈愿系统可以消耗相应道具抽取角色或武器，是游戏中获取新角色和装备的重要方式之一。",
    "source": "genshin_notes.txt"
  },
  {
    "id": "chunk_003",
    "text": "原石是一种重要资源，可以用于兑换纠缠之缘或相遇之缘，也常用于参与祈愿。",
    "source": "genshin_notes.txt"
  },
  {
    "id": "chunk_004",
    "text": "角色养成包括等级提升、武器强化、天赋升级和命之座解锁等内容。",
    "source": "genshin_notes.txt"
  },
  {
    "id": "chunk_005",
    "text": "圣遗物可以提供主属性和副属性，用于提升角色的攻击、防御、生命或元素相关能力。",
    "source": "genshin_notes.txt"
  },
  {
    "id": "chunk_006",
    "text": "元素反应由不同元素相互作用触发，例如蒸发、融化、超载、感电和扩散等。",
    "source": "genshin_notes.txt"
  },
  {
    "id": "chunk_007",
    "text": "原粹树脂是一种体力资源，常用于领取地脉、秘境和首领挑战奖励。",
    "source": "genshin_notes.txt"
  }
]